launcher_menus/__init__.py
launcher_menus/__main__.py
launcher_menus/checks.py
launcher_menus/errors.py
launcher_menus/functions.py
launcher_menus/read_config.py
launcher_menus/themes.py
launcher_menus/menu-cfgs/bemenu.yml
launcher_menus/menu-cfgs/dmenu.yml
launcher_menus/menu-cfgs/template.yml
launcher_menus-21.3.1.dist-info/LICENSE
launcher_menus-21.3.1.dist-info/METADATA
launcher_menus-21.3.1.dist-info/WHEEL
launcher_menus-21.3.1.dist-info/entry_points.txt
launcher_menus-21.3.1.dist-info/top_level.txt
launcher_menus-21.3.1.dist-info/RECORD
